{"cameraMode":{"drawMode":0,"name":"Shaded","section":"Shading Mode"},"sceneLighting":false,"audioPlay":false,"sceneViewState":{"m_AlwaysRefresh":false,"showFog":true,"showSkybox":false,"showFlares":true,"showImageEffects":true,"showParticleSystems":true,"showVisualEffectGraphs":true,"m_FxEnabled":false},"in2DMode":false,"pivot":{"x":2249.587890625,"y":-722.3400268554688,"z":4721.7255859375},"rotation":{"x":-0.0704459547996521,"y":-0.339773952960968,"z":0.025530925020575525,"w":-0.9375187754631043},"size":0.8660253882408142,"orthographic":false}